ViT/__init__.py
ViT/train.py
vision_transformer-1.0.0.dist-info/LICENSE
vision_transformer-1.0.0.dist-info/METADATA
vision_transformer-1.0.0.dist-info/WHEEL
vision_transformer-1.0.0.dist-info/top_level.txt
vision_transformer-1.0.0.dist-info/RECORD
