Metadata-Version: 2.1
Name: vision-transformer
Version: 1.0.0
Summary: Flexible Vision Transformer (ViT) model for your needs.
Home-page: https://github.com/T4ras123/Flexible-ViT
Author: vover
Author-email: vovatara123@gmail.com
Classifier: Programming Language :: Python :: 3
Classifier: License :: OSI Approved :: MIT License
Classifier: Operating System :: OS Independent
Requires-Python: >=3.8
License-File: LICENSE
Requires-Dist: torch
Requires-Dist: torchvision
Requires-Dist: einops
Requires-Dist: matplotlib
Requires-Dist: numpy
